_tmap.pypy39-pp73-darwin.so
tmap/embedding.py
tmap/plotting.py
tmap/__init__.py
tmap/core/line.py
tmap/core/__init__.py
tmap/core/tmap_embedding.py
tmap/layout_generators/__init__.py
tmap/layout_generators/annoy_layout_generator.py
tmap/layout_generators/base_layout_generator.py
tmap/layout_generators/builtin_layout_generator.py
tmap/.dylibs/libomp.dylib
tmap/.dylibs/libCOIN.dylib
tmap/.dylibs/libOGDF.dylib
tmap/helpers/__init__.py
tmap/helpers/set_defaults.py
tmap_viz-1.0.16.dist-info/RECORD
tmap_viz-1.0.16.dist-info/WHEEL
tmap_viz-1.0.16.dist-info/top_level.txt
tmap_viz-1.0.16.dist-info/METADATA
