Metadata-Version: 2.1
Name: tmap-viz
Version: 1.0.16
Summary: A Python package for visualizing large, high-dimensional data sets.
Home-page: UNKNOWN
Author: Daniel Probst
Author-email: daenuprobst@gmail.com
License: UNKNOWN
Platform: UNKNOWN
